deepsvr/ClassifyData.py
deepsvr/CreateClassifier.py
deepsvr/PrepareData.py
deepsvr/__init__.py
deepsvr/cli.py
deepsvr-0.0.1.post1.dist-info/DESCRIPTION.rst
deepsvr-0.0.1.post1.dist-info/METADATA
deepsvr-0.0.1.post1.dist-info/RECORD
deepsvr-0.0.1.post1.dist-info/WHEEL
deepsvr-0.0.1.post1.dist-info/entry_points.txt
deepsvr-0.0.1.post1.dist-info/metadata.json
deepsvr-0.0.1.post1.dist-info/top_level.txt
manual_review_classifier/Analysis.py
manual_review_classifier/ClassifierPlots.py
manual_review_classifier/ClassifyData.py
manual_review_classifier/PrepareData.py
manual_review_classifier/ReadCount.py
manual_review_classifier/__init__.py
manual_review_classifier/cli.py
manual_review_classifier/setup.py
manual_review_classifier/utils.py
manual_review_classifier/tests/__init__.py
manual_review_classifier/tests/test_prepareData.py
manual_review_classifier/tests/test_readCount.py
